gemini_cli/__init__.py
gemini_cli/__main__.py
gemini_cli/cli.py
gemini_cli/gemini.py
gemini_cli/util.py
gemini_cli-0.2.4.dist-info/METADATA
gemini_cli-0.2.4.dist-info/WHEEL
gemini_cli-0.2.4.dist-info/entry_points.txt
gemini_cli-0.2.4.dist-info/RECORD
