Metadata-Version: 2.1
Name: gemini-cli
Version: 0.2.4
Summary: google gemini api for terminal (CLI)
License: MIT
Author: hitsmaxft
Author-email: mfthits@gmail.com
Requires-Python: >=3.9,<4.0
Classifier: License :: OSI Approved :: MIT License
Classifier: Programming Language :: Python :: 3
Classifier: Programming Language :: Python :: 3.9
Classifier: Programming Language :: Python :: 3.10
Classifier: Programming Language :: Python :: 3.11
Classifier: Programming Language :: Python :: 3.12
Requires-Dist: google-generativeai (>=0.3.2,<0.4.0)
Requires-Dist: rich (>=13.7.0,<14.0.0)
Requires-Dist: toml (>=0.10.2,<0.11.0)
